suql/__init__.py
suql/agent.py
suql/faiss_embedding.py
suql/free_text_fcns_server.py
suql/postgresql_connection.py
suql/prompt_continuation.py
suql/utils.py
suql/prompts/__init__.py
suql/prompts/answer_qa.prompt
suql/prompts/field_classification.prompt
suql/prompts/if_db_classification.prompt
suql/prompts/opening_hours.prompt
suql/prompts/parser_suql.prompt
suql/prompts/verification.prompt
suql/prompts/yelp_response_SQL.prompt
suql/prompts/yelp_response_no_results.prompt
suql/sql_free_text_support/__init__.py
suql/sql_free_text_support/execute_free_text_sql.py
suql-1.1.6.dist-info/LICENSE
suql-1.1.6.dist-info/METADATA
suql-1.1.6.dist-info/WHEEL
suql-1.1.6.dist-info/top_level.txt
suql-1.1.6.dist-info/RECORD
