Metadata-Version: 2.1
Name: suql
Version: 1.1.6
Summary: Structured and Unstructured Query Language (SUQL) Python API
Home-page: https://github.com/stanford-oval/suql
Author: Shicheng Liu
Author-email: shicheng@cs.stanford.edu
Classifier: License :: OSI Approved :: Apache Software License
Classifier: Programming Language :: Python :: 3
Classifier: Programming Language :: Python :: 3.8
Classifier: Programming Language :: Python :: 3.9
Classifier: Programming Language :: Python :: 3.10
Classifier: Programming Language :: Python :: 3.11
License-File: LICENSE
Requires-Dist: Jinja2 (==3.1.2)
Requires-Dist: Flask (==2.3.2)
Requires-Dist: Flask-Cors (==4.0.0)
Requires-Dist: Flask-RESTful (==0.3.10)
Requires-Dist: requests (==2.31.0)
Requires-Dist: spacy (==3.6.0)
Requires-Dist: tiktoken (==0.4.0)
Requires-Dist: psycopg2-binary (==2.9.7)
Requires-Dist: pglast (==5.3)
Requires-Dist: FlagEmbedding (~=1.2.5)
Requires-Dist: litellm (==1.34.34)
Requires-Dist: platformdirs (>=4.0.0)
